flask_rak
