Metadata-Version: 1.1
Name: Flask-Rak
Version: 2019.4.8.1
Summary: Rogo apps Kit Development for Rogo Speaker Devices in Python
Home-page: https://github.com/Huong-nt/flask-rak.git
Author: Huong NT
Author-email: huongnt_bk@hotmail.com
License: Apache 2.0
Download-URL: https://codeload.github.com/Huong-nt/flask-rak/tar.gz/2019.04.08.1
Platform: any
Classifier: License :: OSI Approved :: Apache Software License
Classifier: Framework :: Flask
Classifier: Programming Language :: Python
Classifier: Environment :: Web Environment
Classifier: Intended Audience :: Developers
Classifier: Operating System :: OS Independent
Classifier: Topic :: Internet :: WWW/HTTP :: Dynamic Content
Classifier: Topic :: Software Development :: Libraries :: Python Modules
